ld_platform/__init__.py
ld_platform/ld_connector.py
ld_platform/ld_context.py
ld_platform/load_context.py
ld_platform-0.2.0.dist-info/METADATA
ld_platform-0.2.0.dist-info/WHEEL
ld_platform-0.2.0.dist-info/top_level.txt
ld_platform-0.2.0.dist-info/RECORD
